edval2mb/__init__.py
edval2mb/cli/cli_help_strings.py
edval2mb/cli/main.py
edval2mb/converter.py
edval2mb-0.3.4.dist-info/entry_points.txt
edval2mb-0.3.4.dist-info/WHEEL
edval2mb-0.3.4.dist-info/METADATA
edval2mb-0.3.4.dist-info/RECORD
