Metadata-Version: 2.1
Name: edval2mb
Version: 0.3.4
Summary: Convert edval export to ManageBac CSV upload for timetables
License: MIT
Author: Adam Morris
Author-email: classroomtechtools.ctt@gmail.com
Requires-Python: >=3.9,<4.0
Classifier: License :: OSI Approved :: MIT License
Classifier: Programming Language :: Python :: 3
Classifier: Programming Language :: Python :: 3.10
Classifier: Programming Language :: Python :: 3.9
Requires-Dist: click (>=8.1.3,<9.0.0)
Requires-Dist: click-config-file (>=0.6.0,<0.7.0)
Requires-Dist: pandas (>=1.4.3,<2.0.0)
